README.md
setup.py
beeline_portal/__init__.py
beeline_portal/client.py
beeline_portal/errors.py
beeline_portal/models.py
beeline_portal/utils.py
beeline_portal.egg-info/PKG-INFO
beeline_portal.egg-info/SOURCES.txt
beeline_portal.egg-info/dependency_links.txt
beeline_portal.egg-info/requires.txt
beeline_portal.egg-info/top_level.txt