Metadata-Version: 2.1
Name: beeline-portal
Version: 0.0.4
Summary: Beeline cloudpbx portal api wrapper
Home-page: https://github.com/bzdvdn/beeline_portal
Author: bzdvdn
Author-email: bzdv.dn@gmail.com
License: MIT
Platform: UNKNOWN
Requires-Python: >=3.7
